BroadSword/BroadSword.py
BroadSword/__init__.py
BroadSword/libmatrices.so
BroadSword/libmatrices_ARM64.dylib
BroadSword/libmatrices_x86_64.dylib
BroadSword/matrices.c
BroadSword-0.2.2.dist-info/LICENSE
BroadSword-0.2.2.dist-info/METADATA
BroadSword-0.2.2.dist-info/WHEEL
BroadSword-0.2.2.dist-info/top_level.txt
BroadSword-0.2.2.dist-info/zip-safe
BroadSword-0.2.2.dist-info/RECORD
