Metadata-Version: 2.1
Name: BroadSword
Version: 0.2.2
Summary: Python script to broaden calculated spectra from Wien2k and compare to experimental data at the REIXS Beamline at the Canadian Light Source, Saskatoon, Canada.
Home-page: https://github.com/Cody-Somers/BroadSword
Author: Cody Somers
Author-email: cas003@usask.ca
Project-URL: Beamline Information, https://reixs.lightsource.ca
Classifier: Programming Language :: Python :: 3
Classifier: License :: OSI Approved :: MIT License
Classifier: Operating System :: OS Independent
Requires-Python: >=3.6
License-File: LICENSE
Requires-Dist: numpy
Requires-Dist: pandas
Requires-Dist: bokeh (<3,>=2.3.3)
Requires-Dist: reixs
